lussac/__init__.py
lussac/main.py
lussac/core/__init__.py
lussac/core/lussac_data.py
lussac/core/lussac_params.py
lussac/core/module.py
lussac/core/module_factory.py
lussac/core/pipeline.py
lussac/core/spike_sorting.py
lussac/modules/__init__.py
lussac/modules/align_units.py
lussac/modules/export_to_phy.py
lussac/modules/export_to_sigui.py
lussac/modules/find_purkinje_cells.py
lussac/modules/merge_sortings.py
lussac/modules/merge_units.py
lussac/modules/remove_bad_units.py
lussac/modules/remove_duplicated_spikes.py
lussac/modules/remove_redundant_units.py
lussac/modules/units_categorization.py
lussac/params_examples/params_cerebellar_cortex.json
lussac/params_examples/params_synthetic.json
lussac/utils/__init__.py
lussac/utils/misc.py
lussac/utils/plotting.py
lussac/utils/variables.py
lussac-2.0.0b6.post1.dist-info/LICENSE
lussac-2.0.0b6.post1.dist-info/METADATA
lussac-2.0.0b6.post1.dist-info/WHEEL
lussac-2.0.0b6.post1.dist-info/entry_points.txt
lussac-2.0.0b6.post1.dist-info/top_level.txt
lussac-2.0.0b6.post1.dist-info/RECORD
