Metadata-Version: 2.1
Name: lussac
Version: 2.0.0b6.post1
Summary: Python package for automatic post-processing and merging of multiple spike-sorting analyses.
Author-email: Aurélien Wyngaard <aurelien.wyngaard@gmail.com>
Project-URL: homepage, https://github.com/BarbourLab/lussac
Project-URL: repository, https://github.com/BarbourLab/lussac
Project-URL: documentation, https://lussac.readthedocs.io/
Project-URL: changelog, https://github.com/BarbourLab/lussac/releases
Requires-Python: >=3.10
License-File: LICENSE
Requires-Dist: networkx >=3.0
Requires-Dist: numpy >=1.23
Requires-Dist: pandas >=1.4.4
Requires-Dist: scikit-learn >=1.1.0
Requires-Dist: scipy >=1.9
Requires-Dist: plotly >=5.8.2
Requires-Dist: kaleido
Requires-Dist: jsmin >=3.0
Requires-Dist: numba >=0.56.2
Requires-Dist: tqdm >=4.64.0
Requires-Dist: requests >=2.28.0
Requires-Dist: overrides >=7.3.1
Requires-Dist: psutil
Requires-Dist: spikeinterface >=0.101.0rc0
Provides-Extra: dev
Requires-Dist: pytest >=7.1.3 ; extra == 'dev'
Requires-Dist: pytest-cov >=4.0.0 ; extra == 'dev'
Requires-Dist: matplotlib ; extra == 'dev'
Requires-Dist: hdbscan >=0.8.33 ; extra == 'dev'
Requires-Dist: zarr >=2.13.0 ; extra == 'dev'
Requires-Dist: wavpack-numcodecs >=0.1.2 ; extra == 'dev'
Requires-Dist: sphinx >=7.0.1 ; extra == 'dev'
Requires-Dist: sphinxemoji >=0.2.0 ; extra == 'dev'
Requires-Dist: sphinx-rtd-theme >=1.3.0 ; extra == 'dev'
